LICENSE
README.md
simdak/__init__.py
simdak/__main__.py
simdak/config.py
simdak/exception.py
simdak/paud/__init__.py
simdak/paud/auth.py
simdak/paud/base.py
simdak/paud/excel.py
simdak/paud/jenis_penggunaan.py
simdak/paud/paud.py
simdak/paud/rab.py
simdak/paud/rkas.py
simdak/paud/simdak.py
simdak/paud/utils.py
simdak/template/__init__.py
simdak/template/Simdak-Paud.xlsx
simdak/version.py
simdak-1.1.0.dist-info/LICENSE
simdak-1.1.0.dist-info/WHEEL
simdak-1.1.0.dist-info/METADATA
simdak-1.1.0.dist-info/RECORD
