Metadata-Version: 2.1
Name: simdak
Version: 1.1.0
Summary: Importer-exporter data Simdak Kemdikbud
Home-page: https://github.com/dapodix/simdak
License: GPLv3
Author: hexatester
Author-email: habibrohman@gmail.com
Requires-Python: >=3.7,<4.0
Classifier: License :: Other/Proprietary License
Classifier: Programming Language :: Python :: 3
Classifier: Programming Language :: Python :: 3.7
Classifier: Programming Language :: Python :: 3.8
Classifier: Programming Language :: Python :: 3.9
Requires-Dist: bs4 (>=0.0.1,<0.0.2)
Requires-Dist: click (>=7.1.2,<8.0.0)
Requires-Dist: fuzzywuzzy (>=0.18.0,<0.19.0)
Requires-Dist: openpyxl (>=3.0.5,<4.0.0)
Requires-Dist: python-Levenshtein (>=0.12.0,<0.13.0)
Requires-Dist: requests (>=2.25.0,<3.0.0)
Project-URL: Repository, https://github.com/dapodix/simdak
